{"text":
[
{"onset":0,"t":" [Allegro aperto] 1路 "},
{"onset":500,"t":"路 "},
{"onset":1000,"t":"路 "},
{"onset":1500,"t":"路 "},
{"onset":2000,"t":" 2路 "},
{"onset":2500,"t":"路 "},
{"onset":3000,"t":"路 "},
{"onset":3500,"t":"路 "},
{"onset":4000,"t":" 3路 "},
{"onset":4500,"t":"路 "},
{"onset":5000,"t":"路 "},
{"onset":5500,"t":"路 "},
{"onset":6000,"t":" 4路 "},
{"onset":6500,"t":"路 "},
{"onset":7000,"t":"路 "},
{"onset":7500,"t":"路 "},
{"onset":8000,"t":" 5路 "},
{"onset":8500,"t":"路 "},
{"onset":9000,"t":"路 "},
{"onset":9500,"t":"路 "},
{"onset":10000,"t":" 6路 "},
{"onset":10500,"t":"路 "},
{"onset":11000,"t":"路 "},
{"onset":11500,"t":"路 "},
{"onset":12000,"t":" 7路 "},
{"onset":12500,"t":"路 "},
{"onset":13000,"t":"路 "},
{"onset":13500,"t":"路 "},
{"onset":14000,"t":" 8路 "},
{"onset":14500,"t":"路 "},
{"onset":15000,"t":"路 "},
{"onset":15500,"t":"路 "},
{"onset":16000,"t":" 9路 "},
{"onset":16500,"t":"路 "},
{"onset":17000,"t":"路 "},
{"onset":17500,"t":"路 "},
{"onset":18000,"t":" 10路 "},
{"onset":18500,"t":"路 "},
{"onset":19000,"t":"路 "},
{"onset":19500,"t":"路 "},
{"onset":20000,"t":" 11路 "},
{"onset":20500,"t":"路 "},
{"onset":21000,"t":"路 "},
{"onset":21500,"t":"路 "},
{"onset":22000,"t":" 12路 "},
{"onset":22500,"t":"路 "},
{"onset":23000,"t":"路 "},
{"onset":23500,"t":"路 "},
{"onset":24000,"t":" 13路 "},
{"onset":24500,"t":"路 "},
{"onset":25000,"t":"路 "},
{"onset":25500,"t":"路 "},
{"onset":26000,"t":" 14路 "},
{"onset":26500,"t":"路 "},
{"onset":27000,"t":"路 "},
{"onset":27500,"t":"路 "},
{"onset":28000,"t":" 15路 "},
{"onset":28500,"t":"路 "},
{"onset":29000,"t":"路 "},
{"onset":29500,"t":"路 "},
{"onset":30000,"t":" 16路 "},
{"onset":30500,"t":"路 "},
{"onset":31000,"t":"路 "},
{"onset":31500,"t":"路 "},
{"onset":32000,"t":" 17路 "},
{"onset":32500,"t":"路 "},
{"onset":33000,"t":"路 "},
{"onset":33500,"t":"路 "},
{"onset":34000,"t":" 18路 "},
{"onset":34500,"t":"路 "},
{"onset":35000,"t":"路 "},
{"onset":35500,"t":"路 "},
{"onset":36000,"t":" 19路 "},
{"onset":36500,"t":"路 "},
{"onset":37000,"t":"路 "},
{"onset":37500,"t":"路 "},
{"onset":38000,"t":" 20路 "},
{"onset":38500,"t":"路 "},
{"onset":39000,"t":"路 "},
{"onset":39500,"t":"路 "},
{"onset":40000,"t":" 21路 "},
{"onset":40500,"t":"路 "},
{"onset":41000,"t":"路 "},
{"onset":41500,"t":"路 "},
{"onset":42000,"t":" 22路 "},
{"onset":42500,"t":"路 "},
{"onset":43000,"t":"路 "},
{"onset":43500,"t":"路 "},
{"onset":44000,"t":" 23路 "},
{"onset":44500,"t":"路 "},
{"onset":45000,"t":"路 "},
{"onset":45500,"t":"路 "},
{"onset":46000,"t":" 24路 "},
{"onset":46500,"t":"路 "},
{"onset":47000,"t":"路 "},
{"onset":47500,"t":"路 "},
{"onset":48000,"t":" 25路 "},
{"onset":48500,"t":"路 "},
{"onset":49000,"t":"路 "},
{"onset":49500,"t":"路 "},
{"onset":50000,"t":" 26路 "},
{"onset":50500,"t":"路 "},
{"onset":51000,"t":"路 "},
{"onset":51500,"t":"路 "},
{"onset":52000,"t":" 27路 "},
{"onset":52500,"t":"路 "},
{"onset":53000,"t":"路 "},
{"onset":53500,"t":"路 "},
{"onset":54000,"t":" 28路 "},
{"onset":54500,"t":"路 "},
{"onset":55000,"t":"路 "},
{"onset":55500,"t":"路 "},
{"onset":56000,"t":" 29路 "},
{"onset":56500,"t":"路 "},
{"onset":57000,"t":"路 "},
{"onset":57500,"t":"路 "},
{"onset":58000,"t":" 30路 "},
{"onset":58500,"t":"路 "},
{"onset":59000,"t":"路 "},
{"onset":59500,"t":"路 "},
{"onset":60000,"t":" 31路 "},
{"onset":60500,"t":"路 "},
{"onset":61000,"t":"路 "},
{"onset":61500,"t":"路 "},
{"onset":62000,"t":" 32路 "},
{"onset":62500,"t":"路 "},
{"onset":63000,"t":"路 "},
{"onset":63500,"t":"路 "},
{"onset":64000,"t":" 33路 "},
{"onset":64500,"t":"路 "},
{"onset":65000,"t":"路 "},
{"onset":65500,"t":"路 "},
{"onset":66000,"t":" 34路 "},
{"onset":66500,"t":"路 "},
{"onset":67000,"t":"路 "},
{"onset":67500,"t":"路 "},
{"onset":68000,"t":" 35路 "},
{"onset":68500,"t":"路 "},
{"onset":69000,"t":"路 "},
{"onset":69500,"t":"路 "},
{"onset":70000,"t":" 36路 "},
{"onset":70500,"t":"路 "},
{"onset":71000,"t":"路 "},
{"onset":71500,"t":"路 "},
{"onset":72000,"t":" 37路 "},
{"onset":72500,"t":"路 "},
{"onset":73000,"t":"路 "},
{"onset":73500,"t":"路 "},
{"onset":74000,"t":" 38路 "},
{"onset":74500,"t":"路 "},
{"onset":75000,"t":"路 "},
{"onset":75500,"t":"路 "},
{"onset":76000,"t":" 39路 "},
{"onset":76500,"t":"路 "},
{"onset":77000,"t":"路 "},
{"onset":77500,"t":"[fermata] 路 "},
{"onset":78000,"t":" [Adagio] 40路 "},
{"onset":79000,"t":"路 "},
{"onset":80000,"t":"路 "},
{"onset":81000,"t":"路 "},
{"onset":82000,"t":"路 "},
{"onset":83000,"t":"路 "},
{"onset":84000,"t":"路 "},
{"onset":85000,"t":"路 "},
{"onset":86000,"t":" 41路 "},
{"onset":87000,"t":"路 "},
{"onset":88000,"t":"路 "},
{"onset":89000,"t":"路 "},
{"onset":90000,"t":"路 "},
{"onset":91000,"t":"路 "},
{"onset":92000,"t":"路 "},
{"onset":93000,"t":"路 "},
{"onset":94000,"t":" 42路 "},
{"onset":95000,"t":"路 "},
{"onset":96000,"t":"路 "},
{"onset":97000,"t":"路 "},
{"onset":98000,"t":"路 "},
{"onset":99000,"t":"路 "},
{"onset":100000,"t":"路 "},
{"onset":101000,"t":"路 "},
{"onset":102000,"t":" 43路 "},
{"onset":103000,"t":"路 "},
{"onset":104000,"t":"路 "},
{"onset":105000,"t":"路 "},
{"onset":106000,"t":"路 "},
{"onset":107000,"t":"路 "},
{"onset":108000,"t":"路 "},
{"onset":109000,"t":"路 "},
{"onset":110000,"t":" 44路 "},
{"onset":111000,"t":"路 "},
{"onset":112000,"t":"路 "},
{"onset":113000,"t":"路 "},
{"onset":114000,"t":"路 "},
{"onset":115000,"t":"路 "},
{"onset":116000,"t":"路 "},
{"onset":117000,"t":"路 "},
{"onset":118000,"t":" 45路 "},
{"onset":119000,"t":"路 "},
{"onset":120000,"t":"路 "},
{"onset":121000,"t":"路 "},
{"onset":122000,"t":"路 "},
{"onset":123000,"t":"路 "},
{"onset":124000,"t":"路 "},
{"onset":125000,"t":"路 "},
{"onset":126000,"t":" [Allegro aperto] 46路 "},
{"onset":126500,"t":"路 "},
{"onset":127000,"t":"路 "},
{"onset":127500,"t":"路 "},
{"onset":128000,"t":" 47路 "},
{"onset":128500,"t":"路 "},
{"onset":129000,"t":"路 "},
{"onset":129500,"t":"路 "},
{"onset":130000,"t":" 48路 "},
{"onset":130500,"t":"路 "},
{"onset":131000,"t":"路 "},
{"onset":131500,"t":"路 "},
{"onset":132000,"t":" 49路 "},
{"onset":132500,"t":"路 "},
{"onset":133000,"t":"路 "},
{"onset":133500,"t":"路 "},
{"onset":134000,"t":" 50路 "},
{"onset":134500,"t":"路 "},
{"onset":135000,"t":"路 "},
{"onset":135500,"t":"路 "},
{"onset":136000,"t":" 51路 "},
{"onset":136500,"t":"路 "},
{"onset":137000,"t":"路 "},
{"onset":137500,"t":"路 "},
{"onset":138000,"t":" 52路 "},
{"onset":138500,"t":"路 "},
{"onset":139000,"t":"路 "},
{"onset":139500,"t":"路 "},
{"onset":140000,"t":" 53路 "},
{"onset":140500,"t":"路 "},
{"onset":141000,"t":"路 "},
{"onset":141500,"t":"路 "},
{"onset":142000,"t":" 54路 "},
{"onset":142500,"t":"路 "},
{"onset":143000,"t":"路 "},
{"onset":143500,"t":"路 "},
{"onset":144000,"t":" 55路 "},
{"onset":144500,"t":"路 "},
{"onset":145000,"t":"路 "},
{"onset":145500,"t":"路 "},
{"onset":146000,"t":" 56路 "},
{"onset":146500,"t":"路 "},
{"onset":147000,"t":"路 "},
{"onset":147500,"t":"路 "},
{"onset":148000,"t":" 57路 "},
{"onset":148500,"t":"路 "},
{"onset":149000,"t":"路 "},
{"onset":149500,"t":"路 "},
{"onset":150000,"t":" 58路 "},
{"onset":150500,"t":"路 "},
{"onset":151000,"t":"路 "},
{"onset":151500,"t":"路 "},
{"onset":152000,"t":" 59路 "},
{"onset":152500,"t":"路 "},
{"onset":153000,"t":"路 "},
{"onset":153500,"t":"路 "},
{"onset":154000,"t":" 60路 "},
{"onset":154500,"t":"路 "},
{"onset":155000,"t":"路 "},
{"onset":155500,"t":"路 "},
{"onset":156000,"t":" 61路 "},
{"onset":156500,"t":"路 "},
{"onset":157000,"t":"路 "},
{"onset":157500,"t":"路 "},
{"onset":158000,"t":" 62路 "},
{"onset":158500,"t":"路 "},
{"onset":159000,"t":"路 "},
{"onset":159500,"t":"路 "},
{"onset":160000,"t":" 63路 "},
{"onset":160500,"t":"路 "},
{"onset":161000,"t":"路 "},
{"onset":161500,"t":"路 "},
{"onset":162000,"t":" 64路 "},
{"onset":162500,"t":"路 "},
{"onset":163000,"t":"路 "},
{"onset":163500,"t":"路 "},
{"onset":164000,"t":" 65路 "},
{"onset":164500,"t":"路 "},
{"onset":165000,"t":"路 "},
{"onset":165500,"t":"路 "},
{"onset":166000,"t":" 66路 "},
{"onset":166500,"t":"路 "},
{"onset":167000,"t":"路 "},
{"onset":167500,"t":"路 "},
{"onset":168000,"t":" 67路 "},
{"onset":168500,"t":"路 "},
{"onset":169000,"t":"路 "},
{"onset":169500,"t":"路 "},
{"onset":170000,"t":" 68路 "},
{"onset":170500,"t":"路 "},
{"onset":171000,"t":"路 "},
{"onset":171500,"t":"路 "},
{"onset":172000,"t":" 69路 "},
{"onset":172500,"t":"路 "},
{"onset":173000,"t":"路 "},
{"onset":173500,"t":"路 "},
{"onset":174000,"t":" 70路 "},
{"onset":174500,"t":"路 "},
{"onset":175000,"t":"路 "},
{"onset":175500,"t":"路 "},
{"onset":176000,"t":" 71路 "},
{"onset":176500,"t":"路 "},
{"onset":177000,"t":"路 "},
{"onset":177500,"t":"路 "},
{"onset":178000,"t":" 72路 "},
{"onset":178500,"t":"路 "},
{"onset":179000,"t":"路 "},
{"onset":179500,"t":"路 "},
{"onset":180000,"t":" 73路 "},
{"onset":180500,"t":"路 "},
{"onset":181000,"t":"路 "},
{"onset":181500,"t":"路 "},
{"onset":182000,"t":" 74路 "},
{"onset":182500,"t":"路 "},
{"onset":183000,"t":"路 "},
{"onset":183500,"t":"路 "},
{"onset":184000,"t":" 75路 "},
{"onset":184500,"t":"路 "},
{"onset":185000,"t":"路 "},
{"onset":185500,"t":"路 "},
{"onset":186000,"t":" 76路 "},
{"onset":186500,"t":"路 "},
{"onset":187000,"t":"路 "},
{"onset":187500,"t":"路 "},
{"onset":188000,"t":" 77路 "},
{"onset":188500,"t":"路 "},
{"onset":189000,"t":"路 "},
{"onset":189500,"t":"路 "},
{"onset":190000,"t":" 78路 "},
{"onset":190500,"t":"路 "},
{"onset":191000,"t":"路 "},
{"onset":191500,"t":"路 "},
{"onset":192000,"t":" 79路 "},
{"onset":192500,"t":"路 "},
{"onset":193000,"t":"路 "},
{"onset":193500,"t":"路 "},
{"onset":194000,"t":" 80路 "},
{"onset":194500,"t":"路 "},
{"onset":195000,"t":"路 "},
{"onset":195500,"t":"路 "},
{"onset":196000,"t":" 81路 "},
{"onset":196500,"t":"路 "},
{"onset":197000,"t":"路 "},
{"onset":197500,"t":"路 "},
{"onset":198000,"t":" 82路 "},
{"onset":198500,"t":"路 "},
{"onset":199000,"t":"路 "},
{"onset":199500,"t":"路 "},
{"onset":200000,"t":" 83路 "},
{"onset":200500,"t":"路 "},
{"onset":201000,"t":"路 "},
{"onset":201500,"t":"路 "},
{"onset":202000,"t":" 84路 "},
{"onset":202500,"t":"路 "},
{"onset":203000,"t":"路 "},
{"onset":203500,"t":"路 "},
{"onset":204000,"t":" 85路 "},
{"onset":204500,"t":"路 "},
{"onset":205000,"t":"路 "},
{"onset":205500,"t":"路 "},
{"onset":206000,"t":" 86路 "},
{"onset":206500,"t":"路 "},
{"onset":207000,"t":"路 "},
{"onset":207500,"t":"路 "},
{"onset":208000,"t":" 87路 "},
{"onset":208500,"t":"路 "},
{"onset":209000,"t":"路 "},
{"onset":209500,"t":"路 "},
{"onset":210000,"t":" 88路 "},
{"onset":210500,"t":"路 "},
{"onset":211000,"t":"路 "},
{"onset":211500,"t":"路 "},
{"onset":212000,"t":" 89路 "},
{"onset":212500,"t":"路 "},
{"onset":213000,"t":"路 "},
{"onset":213500,"t":"路 "},
{"onset":214000,"t":" 90路 "},
{"onset":214500,"t":"路 "},
{"onset":215000,"t":"路 "},
{"onset":215500,"t":"路 "},
{"onset":216000,"t":" 91路 "},
{"onset":216500,"t":"路 "},
{"onset":217000,"t":"路 "},
{"onset":217500,"t":"路 "},
{"onset":218000,"t":" 92路 "},
{"onset":218500,"t":"路 "},
{"onset":219000,"t":"路 "},
{"onset":219500,"t":"路 "},
{"onset":220000,"t":" 93路 "},
{"onset":220500,"t":"路 "},
{"onset":221000,"t":"路 "},
{"onset":221500,"t":"路 "},
{"onset":222000,"t":" 94路 "},
{"onset":222500,"t":"路 "},
{"onset":223000,"t":"路 "},
{"onset":223500,"t":"路 "},
{"onset":224000,"t":" 95路 "},
{"onset":224500,"t":"路 "},
{"onset":225000,"t":"路 "},
{"onset":225500,"t":"路 "},
{"onset":226000,"t":" 96路 "},
{"onset":226500,"t":"路 "},
{"onset":227000,"t":"路 "},
{"onset":227500,"t":"路 "},
{"onset":228000,"t":" 97路 "},
{"onset":228500,"t":"路 "},
{"onset":229000,"t":"路 "},
{"onset":229500,"t":"路 "},
{"onset":230000,"t":" 98路 "},
{"onset":230500,"t":"路 "},
{"onset":231000,"t":"路 "},
{"onset":231500,"t":"路 "},
{"onset":232000,"t":" 99路 "},
{"onset":232500,"t":"路 "},
{"onset":233000,"t":"路 "},
{"onset":233500,"t":"路 "},
{"onset":234000,"t":" 100路 "},
{"onset":234500,"t":"路 "},
{"onset":235000,"t":"路 "},
{"onset":235500,"t":"路 "},
{"onset":236000,"t":" 101路 "},
{"onset":236500,"t":"路 "},
{"onset":237000,"t":"路 "},
{"onset":237500,"t":"路 "},
{"onset":238000,"t":" 102路 "},
{"onset":238500,"t":"路 "},
{"onset":239000,"t":"路 "},
{"onset":239500,"t":"路 "},
{"onset":240000,"t":" 103路 "},
{"onset":240500,"t":"路 "},
{"onset":241000,"t":"路 "},
{"onset":241500,"t":"路 "},
{"onset":242000,"t":" 104路 "},
{"onset":242500,"t":"路 "},
{"onset":243000,"t":"路 "},
{"onset":243500,"t":"路 "},
{"onset":244000,"t":" 105路 "},
{"onset":244500,"t":"路 "},
{"onset":245000,"t":"路 "},
{"onset":245500,"t":"路 "},
{"onset":246000,"t":" 106路 "},
{"onset":246500,"t":"路 "},
{"onset":247000,"t":"路 "},
{"onset":247500,"t":"路 "},
{"onset":248000,"t":" 107路 "},
{"onset":248500,"t":"路 "},
{"onset":249000,"t":"路 "},
{"onset":249500,"t":"路 "},
{"onset":250000,"t":" 108路 "},
{"onset":250500,"t":"路 "},
{"onset":251000,"t":"路 "},
{"onset":251500,"t":"路 "},
{"onset":252000,"t":" 109路 "},
{"onset":252500,"t":"路 "},
{"onset":253000,"t":"路 "},
{"onset":253500,"t":"路 "},
{"onset":254000,"t":" 110路 "},
{"onset":254500,"t":"路 "},
{"onset":255000,"t":"路 "},
{"onset":255500,"t":"路 "},
{"onset":256000,"t":" 111路 "},
{"onset":256500,"t":"路 "},
{"onset":257000,"t":"路 "},
{"onset":257500,"t":"路 "},
{"onset":258000,"t":" [Tutti] 112路 "},
{"onset":258500,"t":"路 "},
{"onset":259000,"t":"路 "},
{"onset":259500,"t":"路 "},
{"onset":260000,"t":" 113路 "},
{"onset":260500,"t":"路 "},
{"onset":261000,"t":"路 "},
{"onset":261500,"t":"路 "},
{"onset":262000,"t":" 114路 "},
{"onset":262500,"t":"路 "},
{"onset":263000,"t":"路 "},
{"onset":263500,"t":"路 "},
{"onset":264000,"t":" 115路 "},
{"onset":264500,"t":"路 "},
{"onset":265000,"t":"路 "},
{"onset":265500,"t":"路 "},
{"onset":266000,"t":" 116路 "},
{"onset":266500,"t":"路 "},
{"onset":267000,"t":"路 "},
{"onset":267500,"t":"路 "},
{"onset":268000,"t":" 117路 "},
{"onset":268500,"t":"路 "},
{"onset":269000,"t":"路 "},
{"onset":269500,"t":"路 "},
{"onset":270000,"t":" [Solo] 118路 "},
{"onset":270500,"t":"路 "},
{"onset":271000,"t":"路 "},
{"onset":271500,"t":"路 "},
{"onset":272000,"t":" 119路 "},
{"onset":272500,"t":"路 "},
{"onset":273000,"t":"路 "},
{"onset":273500,"t":"路 "},
{"onset":274000,"t":" 120路 "},
{"onset":274500,"t":"路 "},
{"onset":275000,"t":"路 "},
{"onset":275500,"t":"路 "},
{"onset":276000,"t":" 121路 "},
{"onset":276500,"t":"路 "},
{"onset":277000,"t":"路 "},
{"onset":277500,"t":"路 "},
{"onset":278000,"t":" 122路 "},
{"onset":278500,"t":"路 "},
{"onset":279000,"t":"路 "},
{"onset":279500,"t":"路 "},
{"onset":280000,"t":" 123路 "},
{"onset":280500,"t":"路 "},
{"onset":281000,"t":"路 "},
{"onset":281500,"t":"路 "},
{"onset":282000,"t":" 124路 "},
{"onset":282500,"t":"路 "},
{"onset":283000,"t":"路 "},
{"onset":283500,"t":"路 "},
{"onset":284000,"t":" 125路 "},
{"onset":284500,"t":"路 "},
{"onset":285000,"t":"路 "},
{"onset":285500,"t":"路 "},
{"onset":286000,"t":" 126路 "},
{"onset":286500,"t":"路 "},
{"onset":287000,"t":"路 "},
{"onset":287500,"t":"路 "},
{"onset":288000,"t":" 127路 "},
{"onset":288500,"t":"路 "},
{"onset":289000,"t":"路 "},
{"onset":289500,"t":"路 "},
{"onset":290000,"t":" 128路 "},
{"onset":290500,"t":"路 "},
{"onset":291000,"t":"路 "},
{"onset":291500,"t":"路 "},
{"onset":292000,"t":" 129路 "},
{"onset":292500,"t":"路 "},
{"onset":293000,"t":"路 "},
{"onset":293500,"t":"路 "},
{"onset":294000,"t":" 130路 "},
{"onset":294500,"t":"路 "},
{"onset":295000,"t":"路 "},
{"onset":295500,"t":"路 "},
{"onset":296000,"t":" 131路 "},
{"onset":296500,"t":"路 "},
{"onset":297000,"t":"路 "},
{"onset":297500,"t":"路 "},
{"onset":298000,"t":" 132路 "},
{"onset":298500,"t":"路 "},
{"onset":299000,"t":"路 "},
{"onset":299500,"t":"路 "},
{"onset":300000,"t":" 133路 "},
{"onset":300500,"t":"路 "},
{"onset":301000,"t":"路 "},
{"onset":301500,"t":"路 "},
{"onset":302000,"t":" 134路 "},
{"onset":302500,"t":"路 "},
{"onset":303000,"t":"路 "},
{"onset":303500,"t":"路 "},
{"onset":304000,"t":" 135路 "},
{"onset":304500,"t":"路 "},
{"onset":305000,"t":"路 "},
{"onset":305500,"t":"路 "},
{"onset":306000,"t":" 136路 "},
{"onset":306500,"t":"路 "},
{"onset":307000,"t":"路 "},
{"onset":307500,"t":"路 "},
{"onset":308000,"t":" 137路 "},
{"onset":308500,"t":"路 "},
{"onset":309000,"t":"路 "},
{"onset":309500,"t":"路 "},
{"onset":310000,"t":" 138路 "},
{"onset":310500,"t":"路 "},
{"onset":311000,"t":"路 "},
{"onset":311500,"t":"路 "},
{"onset":312000,"t":" 139路 "},
{"onset":312500,"t":"路 "},
{"onset":313000,"t":"路 "},
{"onset":313500,"t":"路 "},
{"onset":314000,"t":" 140路 "},
{"onset":314500,"t":"路 "},
{"onset":315000,"t":"路 "},
{"onset":315500,"t":"路 "},
{"onset":316000,"t":" 141路 "},
{"onset":316500,"t":"路 "},
{"onset":317000,"t":"路 "},
{"onset":317500,"t":"路 "},
{"onset":318000,"t":" 142路 "},
{"onset":318500,"t":"路 "},
{"onset":319000,"t":"路 "},
{"onset":319500,"t":"路 "},
{"onset":320000,"t":" 143路 "},
{"onset":320500,"t":"路 "},
{"onset":321000,"t":"路 "},
{"onset":321500,"t":"路 "},
{"onset":322000,"t":" [Recap] 144路 "},
{"onset":322500,"t":"路 "},
{"onset":323000,"t":"路 "},
{"onset":323500,"t":"路 "},
{"onset":324000,"t":" 145路 "},
{"onset":324500,"t":"路 "},
{"onset":325000,"t":"路 "},
{"onset":325500,"t":"路 "},
{"onset":326000,"t":" 146路 "},
{"onset":326500,"t":"路 "},
{"onset":327000,"t":"路 "},
{"onset":327500,"t":"路 "},
{"onset":328000,"t":" 147路 "},
{"onset":328500,"t":"路 "},
{"onset":329000,"t":"路 "},
{"onset":329500,"t":"路 "},
{"onset":330000,"t":" 148路 "},
{"onset":330500,"t":"路 "},
{"onset":331000,"t":"路 "},
{"onset":331500,"t":"路 "},
{"onset":332000,"t":" 149路 "},
{"onset":332500,"t":"路 "},
{"onset":333000,"t":"路 "},
{"onset":333500,"t":"路 "},
{"onset":334000,"t":" 150路 "},
{"onset":334500,"t":"路 "},
{"onset":335000,"t":"路 "},
{"onset":335500,"t":"路 "},
{"onset":336000,"t":" 151路 "},
{"onset":336500,"t":"路 "},
{"onset":337000,"t":"路 "},
{"onset":337500,"t":"路 "},
{"onset":338000,"t":" 152路 "},
{"onset":338500,"t":"路 "},
{"onset":339000,"t":"路 "},
{"onset":339500,"t":"路 "},
{"onset":340000,"t":" 153路 "},
{"onset":340500,"t":"路 "},
{"onset":341000,"t":"路 "},
{"onset":341500,"t":"路 "},
{"onset":342000,"t":" 154路 "},
{"onset":342500,"t":"路 "},
{"onset":343000,"t":"路 "},
{"onset":343500,"t":"路 "},
{"onset":344000,"t":" 155路 "},
{"onset":344500,"t":"路 "},
{"onset":345000,"t":"路 "},
{"onset":345500,"t":"路 "},
{"onset":346000,"t":" 156路 "},
{"onset":346500,"t":"路 "},
{"onset":347000,"t":"路 "},
{"onset":347500,"t":"路 "},
{"onset":348000,"t":" 157路 "},
{"onset":348500,"t":"路 "},
{"onset":349000,"t":"路 "},
{"onset":349500,"t":"路 "},
{"onset":350000,"t":" 158路 "},
{"onset":350500,"t":"路 "},
{"onset":351000,"t":"路 "},
{"onset":351500,"t":"路 "},
{"onset":352000,"t":" 159路 "},
{"onset":352500,"t":"路 "},
{"onset":353000,"t":"路 "},
{"onset":353500,"t":"路 "},
{"onset":354000,"t":" 160路 "},
{"onset":354500,"t":"路 "},
{"onset":355000,"t":"路 "},
{"onset":355500,"t":"路 "},
{"onset":356000,"t":" 161路 "},
{"onset":356500,"t":"路 "},
{"onset":357000,"t":"路 "},
{"onset":357500,"t":"路 "},
{"onset":358000,"t":" 162路 "},
{"onset":358500,"t":"路 "},
{"onset":359000,"t":"路 "},
{"onset":359500,"t":"路 "},
{"onset":360000,"t":" 163路 "},
{"onset":360500,"t":"路 "},
{"onset":361000,"t":"路 "},
{"onset":361500,"t":"路 "},
{"onset":362000,"t":" 164路 "},
{"onset":362500,"t":"路 "},
{"onset":363000,"t":"路 "},
{"onset":363500,"t":"路 "},
{"onset":364000,"t":" 165路 "},
{"onset":364500,"t":"路 "},
{"onset":365000,"t":"路 "},
{"onset":365500,"t":"路 "},
{"onset":366000,"t":" 166路 "},
{"onset":366500,"t":"路 "},
{"onset":367000,"t":"路 "},
{"onset":367500,"t":"路 "},
{"onset":368000,"t":" 167路 "},
{"onset":368500,"t":"路 "},
{"onset":369000,"t":"路 "},
{"onset":369500,"t":"路 "},
{"onset":370000,"t":" 168路 "},
{"onset":370500,"t":"路 "},
{"onset":371000,"t":"路 "},
{"onset":371500,"t":"路 "},
{"onset":372000,"t":" 169路 "},
{"onset":372500,"t":"路 "},
{"onset":373000,"t":"路 "},
{"onset":373500,"t":"路 "},
{"onset":374000,"t":" 170路 "},
{"onset":374500,"t":"路 "},
{"onset":375000,"t":"路 "},
{"onset":375500,"t":"路 "},
{"onset":376000,"t":" 171路 "},
{"onset":376500,"t":"路 "},
{"onset":377000,"t":"路 "},
{"onset":377500,"t":"路 "},
{"onset":378000,"t":" 172路 "},
{"onset":378500,"t":"路 "},
{"onset":379000,"t":"路 "},
{"onset":379500,"t":"路 "},
{"onset":380000,"t":" 173路 "},
{"onset":380500,"t":"路 "},
{"onset":381000,"t":"路 "},
{"onset":381500,"t":"路 "},
{"onset":382000,"t":" 174路 "},
{"onset":382500,"t":"路 "},
{"onset":383000,"t":"路 "},
{"onset":383500,"t":"路 "},
{"onset":384000,"t":" 175路 "},
{"onset":384500,"t":"路 "},
{"onset":385000,"t":"路 "},
{"onset":385500,"t":"路 "},
{"onset":386000,"t":" 176路 "},
{"onset":386500,"t":"路 "},
{"onset":387000,"t":"路 "},
{"onset":387500,"t":"路 "},
{"onset":388000,"t":" 177路 "},
{"onset":388500,"t":"路 "},
{"onset":389000,"t":"路 "},
{"onset":389500,"t":"路 "},
{"onset":390000,"t":" 178路 "},
{"onset":390500,"t":"路 "},
{"onset":391000,"t":"路 "},
{"onset":391500,"t":"路 "},
{"onset":392000,"t":" 179路 "},
{"onset":392500,"t":"路 "},
{"onset":393000,"t":"路 "},
{"onset":393500,"t":"路 "},
{"onset":394000,"t":" 180路 "},
{"onset":394500,"t":"路 "},
{"onset":395000,"t":"路 "},
{"onset":395500,"t":"路 "},
{"onset":396000,"t":" 181路 "},
{"onset":396500,"t":"路 "},
{"onset":397000,"t":"路 "},
{"onset":397500,"t":"路 "},
{"onset":398000,"t":" 182路 "},
{"onset":398500,"t":"路 "},
{"onset":399000,"t":"路 "},
{"onset":399500,"t":"路 "},
{"onset":400000,"t":" 183路 "},
{"onset":400500,"t":"路 "},
{"onset":401000,"t":"路 "},
{"onset":401500,"t":"路 "},
{"onset":402000,"t":" 184路 "},
{"onset":402500,"t":"路 "},
{"onset":403000,"t":"路 "},
{"onset":403500,"t":"路 "},
{"onset":404000,"t":" 185路 "},
{"onset":404500,"t":"路 "},
{"onset":405000,"t":"路 "},
{"onset":405500,"t":"路 "},
{"onset":406000,"t":" 186路 "},
{"onset":406500,"t":"路 "},
{"onset":407000,"t":"路 "},
{"onset":407500,"t":"路 "},
{"onset":408000,"t":" 187路 "},
{"onset":408500,"t":"路 "},
{"onset":409000,"t":"路 "},
{"onset":409500,"t":"路 "},
{"onset":410000,"t":" 188路 "},
{"onset":410500,"t":"路 "},
{"onset":411000,"t":"路 "},
{"onset":411500,"t":"路 "},
{"onset":412000,"t":" 189路 "},
{"onset":412500,"t":"路 "},
{"onset":413000,"t":"路 "},
{"onset":413500,"t":"路 "},
{"onset":414000,"t":" 190路 "},
{"onset":414500,"t":"路 "},
{"onset":415000,"t":"路 "},
{"onset":415500,"t":"路 "},
{"onset":416000,"t":" 191路 "},
{"onset":416500,"t":"路 "},
{"onset":417000,"t":"路 "},
{"onset":417500,"t":"路 "},
{"onset":418000,"t":" 192路 "},
{"onset":418500,"t":"路 "},
{"onset":419000,"t":"路 "},
{"onset":419500,"t":"路 "},
{"onset":420000,"t":" 193路 "},
{"onset":420500,"t":"路 "},
{"onset":421000,"t":"路 "},
{"onset":421500,"t":"路 "},
{"onset":422000,"t":" 194路 "},
{"onset":422500,"t":"路 "},
{"onset":423000,"t":"路 "},
{"onset":423500,"t":"路 "},
{"onset":424000,"t":" 195路 "},
{"onset":424500,"t":"路 "},
{"onset":425000,"t":"路 "},
{"onset":425500,"t":"路 "},
{"onset":426000,"t":" 196路 "},
{"onset":426500,"t":"路 "},
{"onset":427000,"t":"路 "},
{"onset":427500,"t":"路 "},
{"onset":428000,"t":" 197路 "},
{"onset":428500,"t":"路 "},
{"onset":429000,"t":"路 "},
{"onset":429500,"t":"路 "},
{"onset":430000,"t":" 198路 "},
{"onset":430500,"t":"路 "},
{"onset":431000,"t":"路 "},
{"onset":431500,"t":"路 "},
{"onset":432000,"t":" 199路 "},
{"onset":432500,"t":"路 "},
{"onset":433000,"t":"路 "},
{"onset":433500,"t":"路 "},
{"onset":434000,"t":" 200路 "},
{"onset":434500,"t":"路 "},
{"onset":435000,"t":"路 "},
{"onset":435500,"t":"路 "},
{"onset":436000,"t":" 201路 "},
{"onset":436500,"t":"路 "},
{"onset":437000,"t":"路 "},
{"onset":437500,"t":"路 "},
{"onset":438000,"t":" 202路 "},
{"onset":438500,"t":"路 "},
{"onset":439000,"t":"路 "},
{"onset":439500,"t":"路 "},
{"onset":440000,"t":" 203路 "},
{"onset":440500,"t":"路 "},
{"onset":441000,"t":"路 "},
{"onset":441500,"t":"路 "},
{"onset":442000,"t":" 204路 "},
{"onset":442500,"t":"路 "},
{"onset":443000,"t":"路 "},
{"onset":443500,"t":"路 "},
{"onset":444000,"t":" 205路 "},
{"onset":444500,"t":"路 "},
{"onset":445000,"t":"路 "},
{"onset":445500,"t":"路 "},
{"onset":446000,"t":" 206路 "},
{"onset":446500,"t":"路 "},
{"onset":447000,"t":"路 "},
{"onset":447500,"t":"路 "},
{"onset":448000,"t":" 207路 "},
{"onset":448500,"t":"路 "},
{"onset":449000,"t":"路 "},
{"onset":449500,"t":"路 "},
{"onset":450000,"t":" 208路 "},
{"onset":450500,"t":"路 "},
{"onset":451000,"t":"路 "},
{"onset":451500,"t":"路 "},
{"onset":452000,"t":" 209路 "},
{"onset":452500,"t":"路 "},
{"onset":453000,"t":"路 "},
{"onset":453500,"t":"路 "},
{"onset":454000,"t":" 210路 "},
{"onset":454500,"t":"路 "},
{"onset":455000,"t":"路 "},
{"onset":455500,"t":"路 "},
{"onset":456000,"t":" 211路 "},
{"onset":456500,"t":"路 "},
{"onset":457000,"t":"路 "},
{"onset":457500,"t":"路 "},
{"onset":458000,"t":" 212路 "},
{"onset":458500,"t":"路 "},
{"onset":459000,"t":"路 "},
{"onset":459500,"t":"路 "},
{"onset":460000,"t":" 213路 "},
{"onset":460500,"t":"路 "},
{"onset":461000,"t":"路 "},
{"onset":461500,"t":"路 "},
{"onset":462000,"t":" 214路 "},
{"onset":462500,"t":"路 "},
{"onset":463000,"t":"路 "},
{"onset":463500,"t":"路 "},
{"onset":464000,"t":" 215路 "},
{"onset":464500,"t":"路 "},
{"onset":465000,"t":"路 "},
{"onset":465500,"t":"路 "},
{"onset":466000,"t":" 216路 "},
{"onset":466500,"t":"路 "},
{"onset":467000,"t":"路 "},
{"onset":467500,"t":"路 "},
{"onset":468000,"t":" 217路 "},
{"onset":468500,"t":"路 "},
{"onset":469000,"t":"路 "},
{"onset":469500,"t":"路 "},
{"onset":470000,"t":" 218路 "},
{"onset":470500,"t":"路 "},
{"onset":471000,"t":"路 "},
{"onset":471500,"t":"路 "},
{"onset":472000,"t":" [Cadenza] 219路 "},
{"onset":472500,"t":"路 "},
{"onset":473000,"t":"路 "},
{"onset":473500,"t":"路 "},
{"onset":474000,"t":" [Tutti] 220路 "},
{"onset":474500,"t":"路 "},
{"onset":475000,"t":"路 "},
{"onset":475500,"t":"路 "},
{"onset":476000,"t":" 221路 "},
{"onset":476500,"t":"路 "},
{"onset":477000,"t":"路 "},
{"onset":477500,"t":"路 "},
{"onset":478000,"t":" 222路 "},
{"onset":478500,"t":"路 "},
{"onset":479000,"t":"路 "},
{"onset":479500,"t":"路 "},
{"onset":480000,"t":" 223路 "},
{"onset":480500,"t":"路 "},
{"onset":481000,"t":"路 "},
{"onset":481500,"t":"路 "},
{"onset":482000,"t":" 224路 "},
{"onset":482500,"t":"路 "},
{"onset":483000,"t":"路 "},
{"onset":483500,"t":"路 "},
{"onset":484000,"t":" 225路 "},
{"onset":484500,"t":"路 "},
{"onset":485000,"t":"路 "},
{"onset":485500,"t":"路 "},
{"onset":486000,"t":" 226路 "},
{"onset":486500,"t":"路 "},
{"onset":487000,"t":"路 "},
{"onset":487500,"t":"路 "}
]
}